datazone_provider/__init__.py
datazone_provider/example_dags/sample.py
datazone_provider/hooks/__init__.py
datazone_provider/hooks/datazone.py
datazone_provider/models/execution.py
datazone_provider/operators/__init__.py
datazone_provider/operators/datazone_run_execution.py
datazone_provider/sensors/__init__.py
datazone_provider/sensors/datazone.py
airflow_provider_datazone-1.0.1.dist-info/LICENSE
airflow_provider_datazone-1.0.1.dist-info/METADATA
airflow_provider_datazone-1.0.1.dist-info/WHEEL
airflow_provider_datazone-1.0.1.dist-info/entry_points.txt
airflow_provider_datazone-1.0.1.dist-info/top_level.txt
airflow_provider_datazone-1.0.1.dist-info/RECORD
