Metadata-Version: 2.1
Name: airflow-provider-datazone
Version: 1.0.1
Summary: An Apache Airflow provider package for Datazone
Author-email: Resul Yurttakalan <resul@datazone.co>
License: Apache License 2.0
Project-URL: Homepage, https://datazone.co
Project-URL: Source, https://github.com/datazone/airflow-provider-datazone/
Classifier: Framework :: Apache Airflow
Classifier: Framework :: Apache Airflow :: Provider
Requires-Python: ~=3.8
License-File: LICENSE
Requires-Dist: apache-airflow>=2.4
Requires-Dist: retry==0.9.2
